py3_response_handler/__init__.py
py3_response_handler/requests.py
py3_response_handler-1.0.1.dist-info/LICENSE
py3_response_handler-1.0.1.dist-info/METADATA
py3_response_handler-1.0.1.dist-info/WHEEL
py3_response_handler-1.0.1.dist-info/top_level.txt
py3_response_handler-1.0.1.dist-info/RECORD
