Metadata-Version: 2.1
Name: py3-response-handler
Version: 1.0.1
Summary: A Response Handler Library By Guolei
Home-page: https://github.com/guolei19850528/py3_response_handler
Author: guolei
Author-email: 174000902@qq.com
License: MIT
Requires-Python: >=3.0
License-File: LICENSE
Requires-Dist: requests
Requires-Dist: addict
Requires-Dist: retrying
Requires-Dist: jsonschema
Requires-Dist: xmltodict
Requires-Dist: beautifulsoup4
Requires-Dist: lxml
Requires-Dist: html5lib
